sqlite_migrate/__init__.py
sqlite_migrate/sqlite_utils_plugin.py
sqlite_migrate-0.1a2.dist-info/LICENSE
sqlite_migrate-0.1a2.dist-info/METADATA
sqlite_migrate-0.1a2.dist-info/WHEEL
sqlite_migrate-0.1a2.dist-info/entry_points.txt
sqlite_migrate-0.1a2.dist-info/top_level.txt
sqlite_migrate-0.1a2.dist-info/RECORD
