Metadata-Version: 2.1
Name: sqlite-migrate
Version: 0.1a2
Summary: A simple database migration system for SQLite, based on sqlite-utils
Author: Simon Willison
License: Apache-2.0
Project-URL: Homepage, https://github.com/simonw/sqlite-migrate
Project-URL: Changelog, https://github.com/simonw/sqlite-migrate/releases
Project-URL: Issues, https://github.com/simonw/sqlite-migrate/issues
Classifier: Development Status :: 2 - Pre-Alpha
Provides-Extra: test
License-File: LICENSE
